pharos/__init__.py
pharos/backend.py
pharos/client.py
pharos/exceptions.py
pharos/fields.py
pharos/iterator.py
pharos/jinja.py
pharos/lookups.py
pharos/managers.py
pharos/models.py
pharos/query.py
pharos/utils.py
tests/__init__.py
tests/test_client.py
tests/test_query.py
pharos_k8s-1.0.0a2.dist-info/LICENSE
pharos_k8s-1.0.0a2.dist-info/METADATA
pharos_k8s-1.0.0a2.dist-info/WHEEL
pharos_k8s-1.0.0a2.dist-info/top_level.txt
pharos_k8s-1.0.0a2.dist-info/RECORD
