Metadata-Version: 2.1
Name: pharos-k8s
Version: 1.0.0a2
Summary: Managing Kubernetes resources in Python.
Home-page: https://github.com/Yiling-J/pharos
Author: Yiling
Author-email: njjyl723@gmail.com
License: BSD-3-Clause
Project-URL: Documentation, https://github.com/Yiling-J/pharos
Project-URL: Source, https://github.com/Yiling-J/pharos
Platform: UNKNOWN
Classifier: Development Status :: 2 - Pre-Alpha
Classifier: Environment :: Web Environment
Classifier: Intended Audience :: Developers
Classifier: License :: OSI Approved :: BSD License
Classifier: Operating System :: OS Independent
Classifier: Programming Language :: Python
Classifier: Programming Language :: Python :: 3
Classifier: Programming Language :: Python :: 3 :: Only
Classifier: Programming Language :: Python :: 3.7
Classifier: Programming Language :: Python :: 3.8
Classifier: Programming Language :: Python :: 3.9
Classifier: Topic :: Software Development :: Libraries :: Python Modules
Requires-Python: >=3.7
Requires-Dist: jsonpath-ng
Requires-Dist: kubernetes
Requires-Dist: PyYAML
Requires-Dist: Jinja2
